<?xml version="1.0" encoding="UTF-8" ?>
<CycloneDDS xmlns="https://cdds.io/config"
            xmlns:xsi="http://www.w3.org/2001/XMLSchema-instance"
            xsi:schemaLocation="https://cdds.io/config
            https://raw.githubusercontent.com/eclipse-cyclonedds/cyclonedds/master/etc/cyclonedds.xsd">
  <Domain id="any">
    <General>
      <!-- auto = CycloneDDS picks the best available interface -->
      <!-- When connecting to robot over Ethernet, change to your interface name -->
      <!-- Run 'ip link show' on the Pi to find it (usually eth0 or enp3s0) -->
      <NetworkInterfaceAddress>auto</NetworkInterfaceAddress>
    </General>
    <Discovery>
      <ParticipantIndex>auto</ParticipantIndex>
      <!-- Uncomment and add robot IP when ready to connect:
      <Peers>
        <Peer Address="192.168.123.161"/>
      </Peers>
      -->
    </Discovery>
  </Domain>
</CycloneDDS>
